{"file":"tips.png","frames":{
"tips_bg_00_png":{"x":717,"y":0,"w":253,"h":158,"offX":0,"offY":0,"sourceW":253,"sourceH":158},
"tips_bg_01_png":{"x":0,"y":0,"w":460,"h":92,"offX":0,"offY":0,"sourceW":460,"sourceH":92},
"tips_bg_02_png":{"x":462,"y":0,"w":253,"h":165,"offX":0,"offY":0,"sourceW":253,"sourceH":165},
"tips_bg_dice_png":{"x":727,"y":236,"w":109,"h":114,"offX":0,"offY":0,"sourceW":109,"sourceH":114},
"tips_label_00_png":{"x":838,"y":236,"w":60,"h":26,"offX":0,"offY":0,"sourceW":60,"sourceH":26},
"tips_label_01_png":{"x":327,"y":267,"w":329,"h":23,"offX":0,"offY":0,"sourceW":329,"sourceH":23},
"tips_label_02_png":{"x":334,"y":94,"w":68,"h":28,"offX":0,"offY":0,"sourceW":68,"sourceH":28},
"tips_label_03_png":{"x":334,"y":124,"w":68,"h":26,"offX":0,"offY":1,"sourceW":68,"sourceH":28},
"tips_label_04_png":{"x":327,"y":237,"w":328,"h":28,"offX":32,"offY":0,"sourceW":391,"sourceH":106},
"tips_label_05_png":{"x":727,"y":160,"w":185,"h":74,"offX":81,"offY":0,"sourceW":391,"sourceH":106},
"tips_label_06_png":{"x":0,"y":281,"w":191,"h":29,"offX":100,"offY":39,"sourceW":391,"sourceH":106},
"tips_label_07_png":{"x":0,"y":94,"w":332,"h":106,"offX":30,"offY":0,"sourceW":391,"sourceH":106},
"tips_label_08_png":{"x":334,"y":167,"w":391,"h":68,"offX":0,"offY":1,"sourceW":391,"sourceH":106},
"tips_label_09_png":{"x":1012,"y":0,"w":10,"h":9,"offX":0,"offY":0,"sourceW":65,"sourceH":9},
"tips_label_10_png":{"x":972,"y":80,"w":37,"h":9,"offX":0,"offY":0,"sourceW":65,"sourceH":9},
"tips_label_11_png":{"x":334,"y":152,"w":65,"h":9,"offX":0,"offY":0,"sourceW":65,"sourceH":9},
"tips_label_12_png":{"x":0,"y":202,"w":325,"h":77,"offX":35,"offY":1,"sourceW":391,"sourceH":106},
"tips_paopao_00_png":{"x":972,"y":40,"w":23,"h":38,"offX":0,"offY":0,"sourceW":23,"sourceH":38},
"tips_paopao_01_png":{"x":972,"y":0,"w":38,"h":38,"offX":0,"offY":0,"sourceW":38,"sourceH":38},
"tips_paopao_02_png":{"x":914,"y":160,"w":79,"h":74,"offX":0,"offY":0,"sourceW":79,"sourceH":74}}}